eksipy/__init__.py
eksipy/__main__.py
eksipy/models.py
eksipy-2.0.1.dist-info/LICENSE
eksipy-2.0.1.dist-info/METADATA
eksipy-2.0.1.dist-info/WHEEL
eksipy-2.0.1.dist-info/top_level.txt
eksipy-2.0.1.dist-info/RECORD
