Metadata-Version: 2.1
Name: eksipy
Version: 2.0.1
Summary: Unofficial API for Eksi Sozluk.
Home-page: https://github.com/yusufusta/EksiPy
Author: Yusuf Usta
Author-email: yusuf@usta.email
Maintainer: Yusuf Usta
Maintainer-email: yusuf@usta.email
License: GPL3
Keywords: eksi,eksisozluk,api,eksi-sozluk
Platform: UNKNOWN
Classifier: Intended Audience :: Developers
Classifier: License :: OSI Approved :: GNU General Public License v3 (GPLv3)
Classifier: Programming Language :: Python :: 3.6
Classifier: Programming Language :: Python :: 3.7
Classifier: Programming Language :: Python :: 3.8
Classifier: Programming Language :: Python :: 3.9
Requires-Dist: requests-html
Requires-Dist: requests
